{
  "active": true,
  "format_version": 1,
  "model": {
    "backtest_strategy": "static",
    "calibration": {
      "a": 11.811012531298484,
      "b": -8.642416446077457,
      "fit_version": 2,
      "method": "platt",
      "n": 265414,
      "n_positives": 25,
      "scale": 100.0
    },
    "feature_set": {
      "features": [
        "bafta_nom",
        "bafta_win",
        "berlin_golden_bear",
        "bfi_top_100",
        "biff_nom",
        "biff_win",
        "box_office_roi",
        "cannes_palme_dor",
        "cca_nom",
        "cca_win",
        "cff_nom",
        "cff_win",
        "collection_membership",
        "festival_prestige",
        "has_official_trailer",
        "hfpa_nom",
        "hfpa_win",
        "imdb_rating",
        "imdb_rating_votes",
        "lff_nom",
        "lff_win",
        "metacritic_metascore",
        "nhiff_nom",
        "nhiff_win",
        "nyff_nom",
        "nyff_win",
        "omdb_revenue_domestic",
        "person_quality_score",
        "prior_collab_density",
        "production_country_count",
        "rotten_tomatoes_audience_score",
        "rotten_tomatoes_tomatometer",
        "runtime",
        "sag_nom",
        "sag_win",
        "sff_nom",
        "sff_win",
        "sxsw_nom",
        "sxsw_win",
        "tff_nom",
        "tff_win",
        "tiff_nom",
        "tiff_win",
        "tmdb_budget",
        "tmdb_popularity_score",
        "tmdb_rating",
        "tmdb_rating_votes",
        "tmdb_revenue_worldwide",
        "venice_golden_lion",
        "viff_nom"
      ],
      "granularity": "data_point"
    },
    "holdout_spent_at": "2026-06-04T11:56:10Z",
    "integrity_report": {
      "backtest_strategy": "static",
      "baselines": {
        "popularity": 0.04,
        "prior_rate": 0.0001,
        "random": 0.0
      },
      "brier": 0.0002,
      "granularity": "data_point",
      "holdout_fraction": 0.25,
      "n_evaluated": 265370,
      "n_positives": 25,
      "objective_precision_at_k": 0.2,
      "objective_recall_at_k": 0.2,
      "precision_at_k": 0.2,
      "recall_at_k": 0.2,
      "seed": 20260603,
      "worst_miss": {
        "highest_scored_nonmember": {
          "movie_id": 687,
          "score": 83.2,
          "title": "Saving Private Ryan"
        },
        "lowest_scored_member": {
          "movie_id": 1295,
          "score": 36.8,
          "title": "The Birth of a Nation"
        }
      }
    },
    "lens_config_hash": null,
    "metrics": {
      "brier": 0.0001,
      "precision_at_k": 0.2,
      "recall_at_k": 0.2
    },
    "model_class": "linear_logreg",
    "model_version": 1,
    "run_id": "promote-MPZFTR8Y-bb6545",
    "serialized_model": null,
    "source_key": "afi_100",
    "weights": {
      "bafta_nom": 0.04641668125987053,
      "bafta_win": 0.03572295606136322,
      "berlin_golden_bear": 0.0,
      "bfi_top_100": 0.0,
      "biff_nom": 0.0033764096442610025,
      "biff_win": 0.0033764096442610025,
      "box_office_roi": 0.06708065420389175,
      "cannes_palme_dor": 0.0,
      "cca_nom": 0.0017022567335516214,
      "cca_win": 8.465665741823614e-4,
      "cff_nom": 0.00725954445078969,
      "cff_win": 0.008131167851388454,
      "collection_membership": 0.012544740922749043,
      "festival_prestige": 0.07565012574195862,
      "has_official_trailer": 0.03043704479932785,
      "hfpa_nom": 0.046915359795093536,
      "hfpa_win": 0.04630855843424797,
      "imdb_rating": 0.04075155407190323,
      "imdb_rating_votes": 0.05173514038324356,
      "lff_nom": 0.0,
      "lff_win": 6.348915630951524e-4,
      "metacritic_metascore": 0.07548192888498306,
      "nhiff_nom": 0.0,
      "nhiff_win": 0.0,
      "nyff_nom": 0.02000422589480877,
      "nyff_win": 0.01775633543729782,
      "omdb_revenue_domestic": 0.05185895413160324,
      "person_quality_score": 0.024302994832396507,
      "prior_collab_density": 0.0,
      "production_country_count": 0.0,
      "rotten_tomatoes_audience_score": 0.0,
      "rotten_tomatoes_tomatometer": 0.07850497215986252,
      "runtime": 0.024251654744148254,
      "sag_nom": 0.002499406458809972,
      "sag_win": 0.0016833473928272724,
      "sff_nom": 0.0,
      "sff_win": 0.0,
      "sxsw_nom": 0.0,
      "sxsw_win": 0.0,
      "tff_nom": 0.0,
      "tff_win": 0.0,
      "tiff_nom": 0.0,
      "tiff_win": 0.0,
      "tmdb_budget": 0.060042496770620346,
      "tmdb_popularity_score": 0.013434788212180138,
      "tmdb_rating": 0.04267214611172676,
      "tmdb_rating_votes": 0.031106365844607353,
      "tmdb_revenue_worldwide": 0.06448688358068466,
      "venice_golden_lion": 0.005275743547827005,
      "viff_nom": 0.007747715339064598
    },
    "weights_hash": "6140e89e585e1ca7c0c19fd1fda325e4"
  },
  "pre_registration": {
    "expected_accuracy_range": {
      "max": 1.0,
      "min": 0.0
    },
    "expected_top_features": {
      "note": "ledger-driven promotion (#1061 Session 2)"
    },
    "failure_threshold": "0.0000",
    "notes": null,
    "source_key": "afi_100"
  },
  "source_key": "afi_100",
  "substrate_fingerprint": {
    "lens_config_hash": "565dff513ebe0a96af970169539b8144"
  }
}